<?xml version="1.0"?>
<cena version="0.8.2"><result judgetime="43352.4915186343"><problem title="1.ghillie" filename="" status="14" hash="674401855" detail=""><testcase status="14" exitcode="0" detail="" time="0" memory="0" score="0"/><testcase status="14" exitcode="0" detail="" time="0" memory="0" score="0"/><testcase status="14" exitcode="0" detail="" time="0" memory="0" score="0"/><testcase status="14" exitcode="0" detail="" time="0" memory="0" score="0"/><testcase status="14" exitcode="0" detail="" time="0" memory="0" score="0"/><testcase status="14" exitcode="0" detail="" time="0" memory="0" score="0"/><testcase status="14" exitcode="0" detail="" time="0" memory="0" score="0"/><testcase status="14" exitcode="0" detail="" time="0" memory="0" score="0"/><testcase status="14" exitcode="0" detail="" time="0" memory="0" score="0"/><testcase status="14" exitcode="0" detail="" time="0" memory="0" score="0"/></problem><problem title="2.best" filename="" status="14" hash="0" detail=""><testcase status="14" exitcode="0" detail="" time="0" memory="0" score="0"/><testcase status="14" exitcode="0" detail="" time="0" memory="0" score="0"/><testcase status="14" exitcode="0" detail="" time="0" memory="0" score="0"/><testcase status="14" exitcode="0" detail="" time="0" memory="0" score="0"/><testcase status="14" exitcode="0" detail="" time="0" memory="0" score="0"/><testcase status="14" exitcode="0" detail="" time="0" memory="0" score="0"/><testcase status="14" exitcode="0" detail="" time="0" memory="0" score="0"/><testcase status="14" exitcode="0" detail="" time="0" memory="0" score="0"/><testcase status="14" exitcode="0" detail="" time="0" memory="0" score="0"/><testcase status="14" exitcode="0" detail="" time="0" memory="0" score="0"/></problem><problem title="3.message" filename="" status="14" hash="0" detail=""><testcase status="14" exitcode="0" detail="" time="0" memory="0" score="0"/><testcase status="14" exitcode="0" detail="" time="0" memory="0" score="0"/><testcase status="14" exitcode="0" detail="" time="0" memory="0" score="0"/><testcase status="14" exitcode="0" detail="" time="0" memory="0" score="0"/><testcase status="14" exitcode="0" detail="" time="0" memory="0" score="0"/><testcase status="14" exitcode="0" detail="" time="0" memory="0" score="0"/><testcase status="14" exitcode="0" detail="" time="0" memory="0" score="0"/><testcase status="14" exitcode="0" detail="" time="0" memory="0" score="0"/><testcase status="14" exitcode="0" detail="" time="0" memory="0" score="0"/><testcase status="14" exitcode="0" detail="" time="0" memory="0" score="0"/></problem><problem title="4.tree" filename="" status="14" hash="0" detail=""><testcase status="14" exitcode="0" detail="" time="0" memory="0" score="0"/><testcase status="14" exitcode="0" detail="" time="0" memory="0" score="0"/><testcase status="14" exitcode="0" detail="" time="0" memory="0" score="0"/><testcase status="14" exitcode="0" detail="" time="0" memory="0" score="0"/><testcase status="14" exitcode="0" detail="" time="0" memory="0" score="0"/><testcase status="14" exitcode="0" detail="" time="0" memory="0" score="0"/><testcase status="14" exitcode="0" detail="" time="0" memory="0" score="0"/><testcase status="14" exitcode="0" detail="" time="0" memory="0" score="0"/><testcase status="14" exitcode="0" detail="" time="0" memory="0" score="0"/><testcase status="14" exitcode="0" detail="" time="0" memory="0" score="0"/></problem><problem title="5.car" filename="" status="14" hash="0" detail=""><testcase status="14" exitcode="0" detail="" time="0" memory="0" score="0"/><testcase status="14" exitcode="0" detail="" time="0" memory="0" score="0"/><testcase status="14" exitcode="0" detail="" time="0" memory="0" score="0"/><testcase status="14" exitcode="0" detail="" time="0" memory="0" score="0"/><testcase status="14" exitcode="0" detail="" time="0" memory="0" score="0"/><testcase status="14" exitcode="0" detail="" time="0" memory="0" score="0"/><testcase status="14" exitcode="0" detail="" time="0" memory="0" score="0"/><testcase status="14" exitcode="0" detail="" time="0" memory="0" score="0"/><testcase status="14" exitcode="0" detail="" time="0" memory="0" score="0"/><testcase status="14" exitcode="0" detail="" time="0" memory="0" score="0"/></problem></result></cena>
